amb/__init__.py
amb/__main__.py
amb/apkbuild.py
amb/apkindex.py
amb/architecture.py
amb/cache.py
amb/chroot.py
amb/config.py
amb/logger.py
ambootstrap-0.1.0.dist-info/METADATA
ambootstrap-0.1.0.dist-info/WHEEL
ambootstrap-0.1.0.dist-info/entry_points.txt
ambootstrap-0.1.0.dist-info/top_level.txt
ambootstrap-0.1.0.dist-info/RECORD
