Metadata-Version: 2.1
Name: ambootstrap
Version: 0.1.0
Summary: Tool for bootstrapping Alpine Linux for mobile
Home-page: https://git.sr.ht/~martijnbraam/ambootstrap
Author: Martijn Braam
Author-email: martijn@brixit.nl
License: LGPL3
Classifier: License :: OSI Approved :: GNU Lesser General Public License v3 (LGPLv3)
Classifier: Operating System :: POSIX :: Linux
